{
  "_fv": 10,
  "_type": "biome",
  "definition": {
    "groundBlock": {
      "value": "Blocks.GRASS"
    },
    "undergroundBlock": {
      "value": "Blocks.DIRT#0"
    },
    "generateLakes": true,
    "treeType": 1,
    "vanillaTreeType": "Default",
    "minHeight": 0,
    "spawnVines": false,
    "treeVines": {
      "value": "Blocks.AIR"
    },
    "treeStem": {
      "value": "Blocks.AIR"
    },
    "treeBranch": {
      "value": "Blocks.AIR"
    },
    "treeFruits": {
      "value": "Blocks.AIR"
    },
    "airColor": {
      "value": -65536,
      "falpha": 0.0
    },
    "grassColor": {
      "value": -65536,
      "falpha": 0.0
    },
    "waterColor": {
      "value": -39424,
      "falpha": 0.0
    },
    "treesPerChunk": 0,
    "grassPerChunk": 4,
    "flowersPerChunk": 3,
    "mushroomsPerChunk": 0,
    "bigMushroomsChunk": 0,
    "sandPathcesPerChunk": 0,
    "gravelPatchesPerChunk": 0,
    "reedsPerChunk": 0,
    "cactiPerChunk": 0,
    "rainingPossibility": 0.5,
    "temperature": 1.6,
    "baseHeight": 0.2,
    "heightVariation": 0.1,
    "spawnBiome": true,
    "biomeWeight": 4,
    "biomeType": "DESERT",
    "biomeCategory": "TAIGA",
    "parent": {
      "value": "taiga"
    },
    "biomeDictionaryTypes": [
      "HOT",
      "SAVANNA"
    ],
    "spawnEntries": [
      {
        "entity": {
          "value": "EntityAnimal"
        },
        "minGroup": 1,
        "maxGroup": 15,
        "weight": 15,
        "spawnType": "creature"
      },
      {
        "entity": {
          "value": "CUSTOM:FireWarrior"
        },
        "minGroup": 1,
        "maxGroup": 15,
        "weight": 15,
        "spawnType": "creature"
      },
      {
        "entity": {
          "value": "CUSTOM:FireZombie"
        },
        "minGroup": 1,
        "maxGroup": 15,
        "weight": 15,
        "spawnType": "creature"
      },
      {
        "entity": {
          "value": "EntityMagmaCube"
        },
        "minGroup": 1,
        "maxGroup": 15,
        "weight": 15,
        "spawnType": "creature"
      }
    ]
  }
}